dji3d/__main__.py
dji3d-1.0.0.dist-info/LICENSE
dji3d-1.0.0.dist-info/WHEEL
dji3d-1.0.0.dist-info/METADATA
dji3d-1.0.0.dist-info/RECORD
