Metadata-Version: 2.1
Name: dji3d
Version: 1.0.0
Summary: DJI3D is a tool for graphing 3d positional data extracted from DJI drone telemetry
License: GPLv3
Author: Evan Pratten
Author-email: ewpratten@gmail.com
Requires-Python: >=3.9,<4.0
Classifier: License :: Other/Proprietary License
Classifier: Programming Language :: Python :: 3
Classifier: Programming Language :: Python :: 3.9
Requires-Dist: ffmpeg-python (>=0.2.0,<0.3.0)
Requires-Dist: matplotlib (>=3.3.4,<4.0.0)
Requires-Dist: pysrt (>=1.1.2,<2.0.0)
